narrow_down-1.1.0.dist-info/METADATA
narrow_down-1.1.0.dist-info/WHEEL
narrow_down-1.1.0.dist-info/license_files/LICENSE
narrow_down/hash.py
narrow_down/py.typed
narrow_down/scylladb.py
narrow_down/similarity_store.py
narrow_down/sqlite.py
narrow_down/storage.py
narrow_down/_minhash.py
narrow_down/_rust.pyi
narrow_down/_tokenize.py
narrow_down/__init__.py
narrow_down/_rust.pyd
narrow_down-1.1.0.dist-info/RECORD
