Metadata-Version: 2.1
Name: narrow-down
Version: 1.1.0
Classifier: Development Status :: 4 - Beta
Classifier: Intended Audience :: Developers
Classifier: License :: OSI Approved :: Apache Software License
Classifier: Natural Language :: English
Classifier: Programming Language :: Python :: 3
Classifier: Programming Language :: Python :: 3.7
Classifier: Programming Language :: Python :: 3.8
Classifier: Programming Language :: Python :: 3.9
Classifier: Programming Language :: Python :: 3.10
Requires-Dist: numpy<1.22; python_version < '3.8'
Requires-Dist: numpy; python_version >= '3.8'
Requires-Dist: typing_extensions
Requires-Dist: sphinx; extra == 'docs'
Requires-Dist: myst-parser; extra == 'docs'
Requires-Dist: nbconvert; extra == 'docs'
Requires-Dist: furo; extra == 'docs'
Requires-Dist: pre-commit; extra == 'dev'
Requires-Dist: isort; extra == 'dev'
Requires-Dist: black; extra == 'dev'
Requires-Dist: jupyter; extra == 'dev'
Requires-Dist: nbqa; extra == 'dev'
Requires-Dist: nox; extra == 'dev'
Requires-Dist: mypy; extra == 'dev'
Requires-Dist: mypy-protobuf; extra == 'dev'
Requires-Dist: nbmake; extra == 'dev'
Requires-Dist: bump2version; extra == 'dev'
Requires-Dist: pytest; extra == 'dev'
Requires-Dist: pytest-asyncio; extra == 'dev'
Requires-Dist: pytest-benchmark; extra == 'dev'
Requires-Dist: pytest-profiling; extra == 'dev'
Requires-Dist: xdoctest; extra == 'dev'
Requires-Dist: coverage[toml]; extra == 'dev'
Requires-Dist: pytest-cov; extra == 'dev'
Requires-Dist: watchdog[watchmedo]; extra == 'dev'
Requires-Dist: narrow-down[scylladb,docs]; extra == 'dev'
Requires-Dist: pandas~=1.0; extra == 'experiments'
Requires-Dist: tabulate; extra == 'experiments'
Requires-Dist: tqdm; extra == 'experiments'
Requires-Dist: scylla-driver; extra == 'scylladb'
Provides-Extra: docs
Provides-Extra: dev
Provides-Extra: experiments
Provides-Extra: scylladb
License-File: LICENSE
Summary: Fast fuzzy text search
Keywords: narrow-down,LSH,minhash
Requires-Python: <3.11,>=3.7
Project-URL: documentation, https://chr1st1ank.github.io/narrow-down
Project-URL: repository, https://github.com/chr1st1ank/narrow-down
Project-URL: homepage, https://github.com/chr1st1ank/narrow-down
Project-URL: Bug Tracker, https://github.com/chr1st1ank/narrow-down/issues
